binned_hawkes_multilayer/__init__.py
binned_hawkes_multilayer/ablation.py
binned_hawkes_multilayer/ablation_e2e_test.py
binned_hawkes_multilayer/proposed.py
binned_hawkes_multilayer/proposed_test.py
binned_hawkes_multilayer/residual_analysis.py
binned_hawkes_multilayer/residual_analysis_test.py
binned_hawkes_multilayer/utils.py
binned_hawkes_multilayer/utils_test.py
binned_hawkes_multilayer-0.0.8.dist-info/LICENSE
binned_hawkes_multilayer-0.0.8.dist-info/METADATA
binned_hawkes_multilayer-0.0.8.dist-info/WHEEL
binned_hawkes_multilayer-0.0.8.dist-info/top_level.txt
binned_hawkes_multilayer-0.0.8.dist-info/RECORD
