Metadata-Version: 2.1
Name: binned-hawkes-multilayer
Version: 0.0.8
Summary: A binned Hawkes process for dynamic multilayer graphs.
Author: Matthew Sit
Author-email: matthew.sit22@imperial.ac.uk
License: Apache-2.0
Classifier: License :: OSI Approved :: Apache Software License
License-File: LICENSE
Requires-Dist: matplotlib ==3.6.0
Requires-Dist: numpy ==1.22.4
Requires-Dist: scipy ==1.7.3
Requires-Dist: typing
Requires-Dist: nptyping
Requires-Dist: networkx ==2.8.6
Requires-Dist: pytype
